setup.py
scripts/sinor
sinor/__init__.py
sinor/config.py
sinor/file_util.py
sinor/html_content.py
sinor/markdown_content.py
sinor/posts.py
sinor.egg-info/PKG-INFO
sinor.egg-info/SOURCES.txt
sinor.egg-info/dependency_links.txt
sinor.egg-info/pbr.json
sinor.egg-info/requires.txt
sinor.egg-info/top_level.txt
test/__init__.py
test/data_builder.py
test/test_config.py
test/test_file_util.py
test/test_html_content.py
test/test_markdown_content.py
test/test_posts.py