Metadata-Version: 1.1
Name: sinor
Version: 0.2.0
Summary: Simple blog tool for static websites
Home-page: http://github.com/mahnve/sinor
Author: Marcus Ahnve
Author-email: m@hnve.org
License: UNKNOWN
Download-URL: https://github.com/mahnve/sinor/releases
Platform: UNKNOWN
